LICENSE
README.md
setup.py
src/spm_omega/__init__.py
src/spm_omega/quad.py
src/spm_omega/smooth.py
src/spm_omega/solver_base.py
src/spm_omega/spm.py
src/spm_omega/util.py
src/spm_omega.egg-info/PKG-INFO
src/spm_omega.egg-info/SOURCES.txt
src/spm_omega.egg-info/dependency_links.txt
src/spm_omega.egg-info/requires.txt
src/spm_omega.egg-info/top_level.txt
test/test_quad.py
test/test_solvers.py