Metadata-Version: 2.1
Name: spm-omega
Version: 0.9
Summary: Sparse-modeling solvers for analytic continuation
Home-page: https://github.com/shinaoka/spm_omega/
Author: Hiroshi Shinaoka
Author-email: h.shinaoka@gmail.com
Keywords: sparse modeling
Classifier: Development Status :: 3 - Alpha
Classifier: Intended Audience :: Developers
Classifier: Intended Audience :: Science/Research
Classifier: Topic :: Scientific/Engineering :: Physics
Classifier: License :: OSI Approved :: MIT License
Classifier: Programming Language :: Python :: 3
Requires-Python: >=3
Provides-Extra: test
License-File: LICENSE
